{"name":"MultipeerConnectivity.framework","list":[{"father":"NSObject","childList":["MCAdvertiserAssistant"]},{"father":"UIViewController","childList":["MCBrowserViewController"]},{"father":"NSObject","childList":["MCNearbyDiscoveryPeer"]},{"father":"NSObject","childList":["MCNearbyDiscoveryPeerConnection"]},{"father":"UITableViewCell","childList":["MCNearbyPeerTableViewCell"]},{"father":"UIView","childList":["MCNearbyPeerTableViewHeader"]},{"father":"NSObject","childList":["MCNearbyServiceAdvertiser"]},{"father":"NSObject","childList":["MCNearbyServiceBrowser"]},{"father":"NSObject","childList":["MCNearbyServiceUtils"]},{"father":"NSObject","childList":["MCPeerID"]},{"father":"NSObject","childList":["MCPeerIDInternal"]},{"father":"NSObject","childList":["MCResourceDownloader"]},{"father":"NSObject","childList":["MCResourceProgressObserver"]},{"father":"NSObject","childList":["MCSession"]},{"father":"NSObject","childList":["MCSessionPeerConnectionData"]},{"father":"NSObject","childList":["MCSessionPeerState"]},{"father":"NSObject","childList":["MCSessionStream"]}]}