{
  "name": "SpriteKit.framework",
  "list": [
    {
      "name": "SKAction",
      "parent": null,
      "children": [
        {
          "name": "SKWait",
          "children": [],
          "framework": "SpriteKit.framework"
        }
      ]
    },
    {
      "name": "UIView",
      "parent": null,
      "children": [
        {
          "name": "SKView",
          "children": [],
          "framework": "SpriteKit.framework"
        }
      ]
    },
    {
      "name": "SKNode",
      "parent": null,
      "children": [
        {
          "name": "SKVideoNode",
          "children": [],
          "framework": "SpriteKit.framework"
        }
      ]
    },
    {
      "name": "NSObject",
      "parent": null,
      "children": [
        {
          "name": "SKSoundBuffer",
          "children": [],
          "framework": "SpriteKit.framework"
        },
        {
          "name": "SKSoundContext",
          "children": [],
          "framework": "SpriteKit.framework"
        },
        {
          "name": "SKSoundSource",
          "children": [],
          "framework": "SpriteKit.framework"
        },
        {
          "name": "SKTexture",
          "children": [],
          "framework": "SpriteKit.framework"
        },
        {
          "name": "SKTextureAtlas",
          "children": [],
          "framework": "SpriteKit.framework"
        },
        {
          "name": "SKTextureCache",
          "children": [],
          "framework": "SpriteKit.framework"
        },
        {
          "name": "SKThreadSafeMapTable",
          "children": [],
          "framework": "SpriteKit.framework"
        },
        {
          "name": "SKThreadSafeMutableArray",
          "children": [],
          "framework": "SpriteKit.framework"
        },
        {
          "name": "SKThreadSafeMutableDictionary",
          "children": [],
          "framework": "SpriteKit.framework"
        },
        {
          "name": "SKTransition",
          "children": [],
          "framework": "SpriteKit.framework"
        }
      ]
    },
    {
      "name": "SKEffectNode",
      "parent": null,
      "children": [
        {
          "name": "SKScene",
          "children": [],
          "framework": "SpriteKit.framework"
        }
      ]
    },
    {
      "name": "SKPhysicsJoint",
      "parent": null,
      "children": [
        {
          "name": "SKPhysicsJointFixed",
          "children": [],
          "framework": "SpriteKit.framework"
        },
        {
          "name": "SKPhysicsJointLimit",
          "children": [],
          "framework": "SpriteKit.framework"
        },
        {
          "name": "SKPhysicsJointPin",
          "children": [],
          "framework": "SpriteKit.framework"
        },
        {
          "name": "SKPhysicsJointSliding",
          "children": [],
          "framework": "SpriteKit.framework"
        },
        {
          "name": "SKPhysicsJointSpring",
          "children": [],
          "framework": "SpriteKit.framework"
        }
      ]
    },
    {
      "name": "UIResponder",
      "parent": null,
      "children": [
        {
          "name": "SKNode",
          "children": [],
          "framework": "SpriteKit.framework"
        }
      ]
    },
    {
      "name": "NSKeyedUnarchiver",
      "parent": null,
      "children": [
        {
          "name": "SKKeyedUnarchiver",
          "children": [],
          "framework": "SpriteKit.framework"
        }
      ]
    },
    {
      "name": "SKSpriteNode",
      "parent": null,
      "children": [
        {
          "name": "SKButtonNodeSprite",
          "children": [],
          "framework": "SpriteKit.framework"
        }
      ]
    },
    {
      "name": "SKLabelNode",
      "parent": null,
      "children": [
        {
          "name": "SKButtonNode",
          "children": [],
          "framework": "SpriteKit.framework"
        }
      ]
    }
  ]
}