{
  "name": "ProofReader",
  "list": [
    {
      "name": "PRModification",
      "parent": null,
      "children": [
        {
          "name": "PRZhuyinModification",
          "children": [],
          "framework": "ProofReader"
        }
      ]
    },
    {
      "name": "PRAutocorrectionContext",
      "parent": null,
      "children": [
        {
          "name": "PRZhuyinContext",
          "children": [],
          "framework": "ProofReader"
        }
      ]
    },
    {
      "name": "NSPinyinString",
      "parent": null,
      "children": [
        {
          "name": "PRPinyinString",
          "children": [],
          "framework": "ProofReader"
        }
      ]
    },
    {
      "name": "NSObject",
      "parent": null,
      "children": [
        {
          "name": "AppleSpell",
          "children": [],
          "framework": "ProofReader"
        },
        {
          "name": "PRAutocorrectionContext",
          "children": [],
          "framework": "ProofReader"
        },
        {
          "name": "PRModification",
          "children": [],
          "framework": "ProofReader"
        }
      ]
    }
  ]
}