{
  "name": "ToneLibrary.framework",
  "list": [
    {
      "name": "NSObject",
      "parent": null,
      "children": [
        {
          "name": "TLAccessQueue",
          "children": []
        },
        {
          "name": "TLAlert",
          "children": []
        },
        {
          "name": "TLAlertController",
          "children": []
        },
        {
          "name": "TLITunesTone",
          "children": []
        },
        {
          "name": "TLTextToneInfo",
          "children": []
        },
        {
          "name": "TLToneManager",
          "children": []
        },
        {
          "name": "TLVibrationManager",
          "children": []
        },
        {
          "name": "TLVibrationManagerServiceClient",
          "children": []
        },
        {
          "name": "TLVibrationManagerServiceUtilities",
          "children": []
        },
        {
          "name": "TLVibrationPattern",
          "children": []
        }
      ]
    }
  ]
}